lexi_craft/__init__.py
lexi_craft/lexi_craft.py
lexi_craft-0.2.4.dist-info/METADATA
lexi_craft-0.2.4.dist-info/WHEEL
lexi_craft-0.2.4.dist-info/top_level.txt
lexi_craft-0.2.4.dist-info/RECORD
