Metadata-Version: 2.1
Name: lexi-craft
Version: 0.2.4
Summary: Корректирует текст согласно грамматическим нормам
Home-page: https://github.com/purple-fta/lexi_craft
Author: PurpleFta
Author-email: helloworldfirstfta@gmail.com
Project-URL: GitHub, https://github.com/purple-fta/lexi_craft
Keywords: text correction grammar
Classifier: Programming Language :: Python :: 3.11
Classifier: License :: OSI Approved :: MIT License
Classifier: Operating System :: OS Independent
Requires-Python: >=3.6
Requires-Dist: python-dotenv
Requires-Dist: openai
